icsc_ava_upload_mcp_server/__init__.py
icsc_ava_upload_mcp_server/server.py
mock_file_service/__init__.py
mock_file_service/config.py
mock_file_service/server.py
mock_file_service/handlers/__init__.py
mock_file_service/handlers/backend.py
mock_file_service/handlers/chat.py
mock_file_service/handlers/logs.py
mock_file_service/handlers/resources.py
mock_file_service/storage/uploads/chat/1982361298319/123123123123/Test.docx
mock_file_service/storage/uploads/chat/6900908c351b9eff93aa1117/608d68b9-c14b-49d6-82c0-5085e822f2ce/Hello.docx
mock_file_service/storage/uploads/chat/6900908c351b9eff93aa1117/750e3af8-ab5d-4fe8-98f9-0709c62f83de/Hello.docx
mock_file_service/storage/uploads/chat/6900908c351b9eff93aa1117/ac70280e-59e9-4b8c-b6a6-fb06b7e73a78/Home.docx
mock_file_service/storage/uploads/chat/6900908c351b9eff93aa1117/c7276f87-dbaa-475a-9691-d323fdb24ae2/Play.docx
mock_file_service/storage/uploads/chat/6900908c351b9eff93aa1117/de19eb1e-4f67-4784-90de-86d2e979eaa7/word.docx
icsc_ava_upload_toolkit-0.1.5.dist-info/METADATA
icsc_ava_upload_toolkit-0.1.5.dist-info/WHEEL
icsc_ava_upload_toolkit-0.1.5.dist-info/entry_points.txt
icsc_ava_upload_toolkit-0.1.5.dist-info/licenses/LICENSE
icsc_ava_upload_toolkit-0.1.5.dist-info/RECORD
