Metadata-Version: 2.4
Name: icsc-ava-upload-toolkit
Version: 0.1.5
Summary: ICSC Ava Upload Toolkit - 包含 MCP Server 和 Mock File Service 的完整工具套件
Project-URL: Homepage, https://github.com/your-username/icsc-ava-upload-toolkit
Project-URL: Repository, https://github.com/your-username/icsc-ava-upload-toolkit
Project-URL: Issues, https://github.com/your-username/icsc-ava-upload-toolkit/issues
Author-email: User <user@example.com>
License: MIT
License-File: LICENSE
Requires-Python: >=3.10
Requires-Dist: aiofiles>=23.0.0
Requires-Dist: fastapi>=0.104.0
Requires-Dist: fastmcp>=2.0.0
Requires-Dist: python-multipart>=0.0.6
Requires-Dist: requests>=2.31.0
Requires-Dist: uvicorn>=0.24.0
